setup.py
rpihware/__init__.py
rpihware/elements.py
rpihware.egg-info/PKG-INFO
rpihware.egg-info/SOURCES.txt
rpihware.egg-info/dependency_links.txt
rpihware.egg-info/not-zip-safe
rpihware.egg-info/requires.txt
rpihware.egg-info/top_level.txt